{
  "generated_at": "2025-11-15T00:36:19.904149+08:00",
  "total_titles_processed": 315,
  "failed_sources": [],
  "trends": [
    {
      "keyword_group": "汽车",
      "match_count": 3,
      "titles": [
        {
          "title": "理想汽车发布两起质量事故处理公告，共 18 名员工被问责，能挽回消费者信任吗？哪些后续保障更值得关注？",
          "url": "https://www.zhihu.com/question/1972723249331864758",
          "source": "知乎",
          "ranks": [
            6
          ],
          "is_new": false,
          "appearance_count": 1,
          "time_info": "00时36分"
        },
        {
          "title": "受汽车和家电拖累，中国10月社零同比增速放缓至2.9%，金银珠宝零售同比增长37.6%",
          "url": "https://wallstreetcn.com/articles/3759365",
          "source": "华尔街见闻",
          "ranks": [
            10
          ],
          "is_new": false,
          "appearance_count": 1,
          "time_info": "00时36分"
        },
        {
          "title": "理想汽车内部问责处理18人",
          "url": "https://www.toutiao.com/trending/7572410670306807315/",
          "source": "今日头条",
          "ranks": [
            13
          ],
          "is_new": false,
          "appearance_count": 1,
          "time_info": "00时36分"
        }
      ]
    },
    {
      "keyword_group": "玉米",
      "match_count": 1,
      "titles": [
        {
          "title": "玉米地窜出3头野猪 收割机追截2小时",
          "url": "https://www.toutiao.com/trending/7572559775284920358/",
          "source": "今日头条",
          "ranks": [
            10
          ],
          "is_new": false,
          "appearance_count": 1,
          "time_info": "00时36分"
        }
      ]
    }
  ],
  "report_image_url": "https://github.com/KuanYa/TrendRadar/img/news.jpg"
}